dubclub_allauth/__init__.py
dubclub_allauth/provider.py
dubclub_allauth/urls.py
dubclub_allauth/views.py
dubclub_allauth-0.0.1.dist-info/LICENSE
dubclub_allauth-0.0.1.dist-info/METADATA
dubclub_allauth-0.0.1.dist-info/WHEEL
dubclub_allauth-0.0.1.dist-info/top_level.txt
dubclub_allauth-0.0.1.dist-info/RECORD
