Metadata-Version: 2.1
Name: dubclub-allauth
Version: 0.0.1
Summary: A django-allauth provider to sign-in with DubClub
License: MIT License
Project-URL: Homepage, https://github.com/DubClub-win/dubclub-allauth
Project-URL: Repository, https://github.com/DubClub-win/dubclub-allauth
Project-URL: Bug Reports, https://github.com/DubClub-win/dubclub-allauth/issues
Keywords: DubClub,Django,allauth,OAuth
Classifier: Development Status :: 4 - Beta
Classifier: Framework :: Django :: 4
Classifier: Intended Audience :: Developers
Classifier: License :: OSI Approved :: MIT License
Classifier: Operating System :: OS Independent
Classifier: Programming Language :: Python :: 3
Requires-Python: >=3.8
License-File: LICENSE
Requires-Dist: django (<5.0,>4.0)
Requires-Dist: django-allauth
Requires-Dist: requests
Provides-Extra: dev
Requires-Dist: pip-tools ; extra == 'dev'
